{"config":{"output_file":null,"full_docs":false,"pub_only":false,"reachable_only":false,"distro_crate":false,"signatures":false,"borrow_data":false},"version":"0.19.1","compilation":{"directory":"/Users/wiktor/Desktop/OI/advent_of_code_2021/1/rust_version","program":"/Users/wiktor/.rustup/toolchains/stable-aarch64-apple-darwin/bin/rls","arguments":[],"output":"/Users/wiktor/Desktop/OI/advent_of_code_2021/1/rust_version/target/rls/debug/deps/librust_version-e5b3d1f35c950b58.rmeta"},"prelude":{"crate_id":{"name":"rust_version","disambiguator":[16946341975971925092,0]},"crate_root":"src","external_crates":[{"file_name":"/Users/wiktor/Desktop/OI/advent_of_code_2021/1/rust_version/src/main.rs","num":1,"id":{"name":"std","disambiguator":[7101137524639191865,0]}},{"file_name":"/Users/wiktor/Desktop/OI/advent_of_code_2021/1/rust_version/src/main.rs","num":2,"id":{"name":"core","disambiguator":[1887987468260230341,0]}},{"file_name":"/Users/wiktor/Desktop/OI/advent_of_code_2021/1/rust_version/src/main.rs","num":3,"id":{"name":"compiler_builtins","disambiguator":[11423829060327785168,0]}},{"file_name":"/Users/wiktor/Desktop/OI/advent_of_code_2021/1/rust_version/src/main.rs","num":4,"id":{"name":"rustc_std_workspace_core","disambiguator":[11467597086512816709,0]}},{"file_name":"/Users/wiktor/Desktop/OI/advent_of_code_2021/1/rust_version/src/main.rs","num":5,"id":{"name":"alloc","disambiguator":[11478090127832647137,0]}},{"file_name":"/Users/wiktor/Desktop/OI/advent_of_code_2021/1/rust_version/src/main.rs","num":6,"id":{"name":"libc","disambiguator":[16011649288231704614,0]}},{"file_name":"/Users/wiktor/Desktop/OI/advent_of_code_2021/1/rust_version/src/main.rs","num":7,"id":{"name":"unwind","disambiguator":[12732930576792739361,0]}},{"file_name":"/Users/wiktor/Desktop/OI/advent_of_code_2021/1/rust_version/src/main.rs","num":8,"id":{"name":"cfg_if","disambiguator":[11329576585081918948,0]}},{"file_name":"/Users/wiktor/Desktop/OI/advent_of_code_2021/1/rust_version/src/main.rs","num":9,"id":{"name":"hashbrown","disambiguator":[17189205392791100154,0]}},{"file_name":"/Users/wiktor/Desktop/OI/advent_of_code_2021/1/rust_version/src/main.rs","num":10,"id":{"name":"rustc_std_workspace_alloc","disambiguator":[2953602047458512213,0]}},{"file_name":"/Users/wiktor/Desktop/OI/advent_of_code_2021/1/rust_version/src/main.rs","num":11,"id":{"name":"rustc_demangle","disambiguator":[4833631622402917298,0]}},{"file_name":"/Users/wiktor/Desktop/OI/advent_of_code_2021/1/rust_version/src/main.rs","num":12,"id":{"name":"std_detect","disambiguator":[2052285648718182991,0]}},{"file_name":"/Users/wiktor/Desktop/OI/advent_of_code_2021/1/rust_version/src/main.rs","num":13,"id":{"name":"addr2line","disambiguator":[16253613530580249776,0]}},{"file_name":"/Users/wiktor/Desktop/OI/advent_of_code_2021/1/rust_version/src/main.rs","num":14,"id":{"name":"gimli","disambiguator":[5745760535571076062,0]}},{"file_name":"/Users/wiktor/Desktop/OI/advent_of_code_2021/1/rust_version/src/main.rs","num":15,"id":{"name":"object","disambiguator":[7876989589743503273,0]}},{"file_name":"/Users/wiktor/Desktop/OI/advent_of_code_2021/1/rust_version/src/main.rs","num":16,"id":{"name":"memchr","disambiguator":[14488000063334320346,0]}},{"file_name":"/Users/wiktor/Desktop/OI/advent_of_code_2021/1/rust_version/src/main.rs","num":17,"id":{"name":"panic_unwind","disambiguator":[5084180220498965168,0]}}],"span":{"file_name":"src/main.rs","byte_start":0,"byte_end":581,"line_start":1,"line_end":24,"column_start":1,"column_end":2}},"imports":[{"kind":"Use","ref_id":{"krate":2,"index":27016},"span":{"file_name":"src/main.rs","byte_start":14,"byte_end":22,"line_start":1,"line_end":1,"column_start":15,"column_end":23},"alias_span":null,"name":"Ordering","value":"","parent":{"krate":0,"index":0}},{"kind":"Use","ref_id":{"krate":1,"index":3191},"span":{"file_name":"src/main.rs","byte_start":33,"byte_end":35,"line_start":2,"line_end":2,"column_start":10,"column_end":12},"alias_span":null,"name":"io","value":"","parent":{"krate":0,"index":0}}],"defs":[{"kind":"Mod","id":{"krate":0,"index":0},"span":{"file_name":"src/main.rs","byte_start":0,"byte_end":581,"line_start":1,"line_end":24,"column_start":1,"column_end":2},"name":"","qualname":"::","value":"src/main.rs","parent":null,"children":[{"krate":0,"index":1},{"krate":0,"index":2},{"krate":0,"index":3},{"krate":0,"index":6},{"krate":0,"index":9}],"decl_id":null,"docs":"","sig":null,"attributes":[]},{"kind":"Function","id":{"krate":0,"index":9},"span":{"file_name":"src/main.rs","byte_start":41,"byte_end":45,"line_start":4,"line_end":4,"column_start":4,"column_end":8},"name":"main","qualname":"::main","value":"fn main() -> io::Result<()>","parent":null,"children":[],"decl_id":null,"docs":"","sig":null,"attributes":[]},{"kind":"Local","id":{"krate":0,"index":536870921},"span":{"file_name":"src/main.rs","byte_start":80,"byte_end":86,"line_start":5,"line_end":5,"column_start":13,"column_end":19},"name":"answer","qualname":"answer$HirId { owner: DefId(0:9 ~ rust_version[eb2d]::main), local_id: 4 }","value":"i32","parent":null,"children":[],"decl_id":null,"docs":"","sig":null,"attributes":[]},{"kind":"Local","id":{"krate":0,"index":3489660937},"span":{"file_name":"src/main.rs","byte_start":104,"byte_end":112,"line_start":6,"line_end":6,"column_start":13,"column_end":21},"name":"previous","qualname":"previous$HirId { owner: DefId(0:9 ~ rust_version[eb2d]::main), local_id: 11 }","value":"i32","parent":null,"children":[],"decl_id":null,"docs":"","sig":null,"attributes":[]},{"kind":"Local","id":{"krate":0,"index":3355443209},"span":{"file_name":"src/main.rs","byte_start":157,"byte_end":163,"line_start":8,"line_end":8,"column_start":17,"column_end":23},"name":"number","qualname":"number$HirId { owner: DefId(0:9 ~ rust_version[eb2d]::main), local_id: 19 }","value":"std::string::String","parent":null,"children":[],"decl_id":null,"docs":"","sig":null,"attributes":[]},{"kind":"Local","id":{"krate":0,"index":3959422985},"span":{"file_name":"src/main.rs","byte_start":287,"byte_end":290,"line_start":12,"line_end":12,"column_start":16,"column_end":19},"name":"num","qualname":"num$HirId { owner: DefId(0:9 ~ rust_version[eb2d]::main), local_id: 55 }","value":"i32","parent":null,"children":[],"decl_id":null,"docs":"","sig":null,"attributes":[]}],"impls":[],"refs":[{"kind":"Mod","span":{"file_name":"src/main.rs","byte_start":4,"byte_end":7,"line_start":1,"line_end":1,"column_start":5,"column_end":8},"ref_id":{"krate":1,"index":0}},{"kind":"Mod","span":{"file_name":"src/main.rs","byte_start":9,"byte_end":12,"line_start":1,"line_end":1,"column_start":10,"column_end":13},"ref_id":{"krate":2,"index":2638}},{"kind":"Mod","span":{"file_name":"src/main.rs","byte_start":28,"byte_end":31,"line_start":2,"line_end":2,"column_start":5,"column_end":8},"ref_id":{"krate":1,"index":0}},{"kind":"Type","span":{"file_name":"src/main.rs","byte_start":55,"byte_end":61,"line_start":4,"line_end":4,"column_start":18,"column_end":24},"ref_id":{"krate":1,"index":3791}},{"kind":"Mod","span":{"file_name":"src/main.rs","byte_start":51,"byte_end":53,"line_start":4,"line_end":4,"column_start":14,"column_end":16},"ref_id":{"krate":1,"index":3191}},{"kind":"Variable","span":{"file_name":"src/main.rs","byte_start":125,"byte_end":128,"line_start":6,"line_end":6,"column_start":34,"column_end":37},"ref_id":{"krate":2,"index":14499}},{"kind":"Mod","span":{"file_name":"src/main.rs","byte_start":115,"byte_end":118,"line_start":6,"line_end":6,"column_start":24,"column_end":27},"ref_id":{"krate":1,"index":0}},{"kind":"Mod","span":{"file_name":"src/main.rs","byte_start":120,"byte_end":123,"line_start":6,"line_end":6,"column_start":29,"column_end":32},"ref_id":{"krate":2,"index":67}},{"kind":"Function","span":{"file_name":"src/main.rs","byte_start":174,"byte_end":177,"line_start":8,"line_end":8,"column_start":34,"column_end":37},"ref_id":{"krate":5,"index":5484}},{"kind":"Type","span":{"file_name":"src/main.rs","byte_start":166,"byte_end":172,"line_start":8,"line_end":8,"column_start":26,"column_end":32},"ref_id":{"krate":5,"index":7547}},{"kind":"Function","span":{"file_name":"src/main.rs","byte_start":201,"byte_end":210,"line_start":9,"line_end":9,"column_start":21,"column_end":30},"ref_id":{"krate":1,"index":4100}},{"kind":"Function","span":{"file_name":"src/main.rs","byte_start":193,"byte_end":198,"line_start":9,"line_end":9,"column_start":13,"column_end":18},"ref_id":{"krate":1,"index":4094}},{"kind":"Mod","span":{"file_name":"src/main.rs","byte_start":189,"byte_end":191,"line_start":9,"line_end":9,"column_start":9,"column_end":11},"ref_id":{"krate":1,"index":3191}},{"kind":"Variable","span":{"file_name":"src/main.rs","byte_start":216,"byte_end":222,"line_start":9,"line_end":9,"column_start":36,"column_end":42},"ref_id":{"krate":0,"index":3355443209}},{"kind":"Function","span":{"file_name":"src/main.rs","byte_start":255,"byte_end":260,"line_start":11,"line_end":11,"column_start":29,"column_end":34},"ref_id":{"krate":2,"index":12338}},{"kind":"Function","span":{"file_name":"src/main.rs","byte_start":248,"byte_end":252,"line_start":11,"line_end":11,"column_start":22,"column_end":26},"ref_id":{"krate":2,"index":12309}},{"kind":"Variable","span":{"file_name":"src/main.rs","byte_start":241,"byte_end":247,"line_start":11,"line_end":11,"column_start":15,"column_end":21},"ref_id":{"krate":0,"index":3355443209}},{"kind":"Type","span":{"file_name":"src/main.rs","byte_start":284,"byte_end":286,"line_start":12,"line_end":12,"column_start":13,"column_end":15},"ref_id":{"krate":2,"index":36832}},{"kind":"Type","span":{"file_name":"src/main.rs","byte_start":284,"byte_end":286,"line_start":12,"line_end":12,"column_start":13,"column_end":15},"ref_id":{"krate":2,"index":36832}},{"kind":"Function","span":{"file_name":"src/main.rs","byte_start":323,"byte_end":326,"line_start":13,"line_end":13,"column_start":27,"column_end":30},"ref_id":{"krate":2,"index":2677}},{"kind":"Variable","span":{"file_name":"src/main.rs","byte_start":319,"byte_end":322,"line_start":13,"line_end":13,"column_start":23,"column_end":26},"ref_id":{"krate":0,"index":3959422985}},{"kind":"Variable","span":{"file_name":"src/main.rs","byte_start":328,"byte_end":336,"line_start":13,"line_end":13,"column_start":32,"column_end":40},"ref_id":{"krate":0,"index":3489660937}},{"kind":"Type","span":{"file_name":"src/main.rs","byte_start":370,"byte_end":377,"line_start":14,"line_end":14,"column_start":31,"column_end":38},"ref_id":{"krate":2,"index":27023}},{"kind":"Type","span":{"file_name":"src/main.rs","byte_start":360,"byte_end":368,"line_start":14,"line_end":14,"column_start":21,"column_end":29},"ref_id":{"krate":2,"index":27016}},{"kind":"Type","span":{"file_name":"src/main.rs","byte_start":370,"byte_end":377,"line_start":14,"line_end":14,"column_start":31,"column_end":38},"ref_id":{"krate":2,"index":27023}},{"kind":"Type","span":{"file_name":"src/main.rs","byte_start":360,"byte_end":368,"line_start":14,"line_end":14,"column_start":21,"column_end":29},"ref_id":{"krate":2,"index":27016}},{"kind":"Variable","span":{"file_name":"src/main.rs","byte_start":381,"byte_end":387,"line_start":14,"line_end":14,"column_start":42,"column_end":48},"ref_id":{"krate":0,"index":536870921}},{"kind":"Variable","span":{"file_name":"src/main.rs","byte_start":469,"byte_end":472,"line_start":17,"line_end":17,"column_start":28,"column_end":31},"ref_id":{"krate":0,"index":3959422985}},{"kind":"Variable","span":{"file_name":"src/main.rs","byte_start":458,"byte_end":466,"line_start":17,"line_end":17,"column_start":17,"column_end":25},"ref_id":{"krate":0,"index":3489660937}},{"kind":"Type","span":{"file_name":"src/main.rs","byte_start":500,"byte_end":503,"line_start":19,"line_end":19,"column_start":13,"column_end":16},"ref_id":{"krate":2,"index":36835}},{"kind":"Type","span":{"file_name":"src/main.rs","byte_start":500,"byte_end":503,"line_start":19,"line_end":19,"column_start":13,"column_end":16},"ref_id":{"krate":2,"index":36835}},{"kind":"Variable","span":{"file_name":"src/main.rs","byte_start":560,"byte_end":566,"line_start":22,"line_end":22,"column_start":28,"column_end":34},"ref_id":{"krate":0,"index":536870921}},{"kind":"Type","span":{"file_name":"src/main.rs","byte_start":573,"byte_end":575,"line_start":23,"line_end":23,"column_start":5,"column_end":7},"ref_id":{"krate":2,"index":36832}}],"macro_refs":[],"relations":[]}